[{"TANGGAL":"2019-01-06","SAMPAH COMPECTOR":"179200","MAKAM MATARAM":"17750","KEMBANG KUNING":"19130","TAMBAK REJO":"13340","KENDANGSARI":0},{"TANGGAL":"2019-01-07","SAMPAH COMPECTOR":"456370","MAKAM MATARAM":"16370","KEMBANG KUNING":"24060","TAMBAK REJO":"31020","KENDANGSARI":"17790"},{"TANGGAL":"2019-01-08","SAMPAH COMPECTOR":"526480","MAKAM MATARAM":"34590","KEMBANG KUNING":"31640","TAMBAK REJO":"30600","KENDANGSARI":"11550"},{"TANGGAL":"2019-01-09","SAMPAH COMPECTOR":"515860","MAKAM MATARAM":"32270","KEMBANG KUNING":"19070","TAMBAK REJO":"26280","KENDANGSARI":"16020"},{"TANGGAL":"2019-01-10","SAMPAH COMPECTOR":"534680","MAKAM MATARAM":"54030","KEMBANG KUNING":"33360","TAMBAK REJO":"30580","KENDANGSARI":"29330"}]